.eslintignore
.eslintrc
.mailmap
.pylintrc
.testr.conf
AUTHORS
CONTRIBUTING.rst
ChangeLog
HACKING.rst
LICENSE
MANIFEST.in
Makefile
README.rst
babel-django.cfg
babel-djangojs.cfg
manage.py
package.json
requirements.txt
run_tests.sh
setup.cfg
setup.py
test-requirements.txt
test-shim.js
tox.ini
doc/Makefile
doc/source/conf.py
doc/source/contributing.rst
doc/source/faq.rst
doc/source/glossary.rst
doc/source/index.rst
doc/source/intro.rst
doc/source/plugin_registry.rst
doc/source/quickstart.rst
doc/source/testing.rst
doc/source/ref/context_processors.rst
doc/source/ref/decorators.rst
doc/source/ref/exceptions.rst
doc/source/ref/forms.rst
doc/source/ref/horizon.rst
doc/source/ref/local_conf.rst
doc/source/ref/middleware.rst
doc/source/ref/run_tests.rst
doc/source/ref/tables.rst
doc/source/ref/tabs.rst
doc/source/ref/test.rst
doc/source/ref/workflows.rst
doc/source/releases/2012_1.rst
doc/source/releases/2012_2.rst
doc/source/releases/2013_1.rst
doc/source/releases/2013_2.rst
doc/source/releases/2014_1.rst
doc/source/releases/2014_2.rst
doc/source/releases/2015_1.rst
doc/source/releases/8.0.0.rst
doc/source/topics/angularjs.rst
doc/source/topics/customizing.rst
doc/source/topics/deployment.rst
doc/source/topics/install.rst
doc/source/topics/javascript_testing.rst
doc/source/topics/packaging.rst
doc/source/topics/policy.rst
doc/source/topics/settings.rst
doc/source/topics/styling.rst
doc/source/topics/table_actions.rst
doc/source/topics/tables.rst
doc/source/topics/testing.rst
doc/source/topics/workflows.rst
doc/source/tutorials/dashboard.rst
doc/source/tutorials/plugin.rst
horizon/__init__.py
horizon/base.py
horizon/context_processors.py
horizon/decorators.py
horizon/exceptions.py
horizon/karma.conf.js
horizon/loaders.py
horizon/messages.py
horizon/middleware.py
horizon/notifications.py
horizon/site_urls.py
horizon/themes.py
horizon/version.py
horizon/views.py
horizon/browsers/__init__.py
horizon/browsers/base.py
horizon/browsers/breadcrumb.py
horizon/browsers/views.py
leonardo_horizon.egg-info/PKG-INFO
leonardo_horizon.egg-info/SOURCES.txt
leonardo_horizon.egg-info/dependency_links.txt
leonardo_horizon.egg-info/not-zip-safe
leonardo_horizon.egg-info/pbr.json
leonardo_horizon.egg-info/requires.txt
leonardo_horizon.egg-info/top_level.txt
